hotels_mcp/__init__.py
hotels_mcp/hotels_server.py
iflow_mcp_hotels_mcp_server-0.1.0.dist-info/METADATA
iflow_mcp_hotels_mcp_server-0.1.0.dist-info/WHEEL
iflow_mcp_hotels_mcp_server-0.1.0.dist-info/entry_points.txt
iflow_mcp_hotels_mcp_server-0.1.0.dist-info/top_level.txt
iflow_mcp_hotels_mcp_server-0.1.0.dist-info/RECORD
