Metadata-Version: 2.4
Name: iflow-mcp-hotels-mcp-server
Version: 0.1.0
Summary: Add your description here
Requires-Python: >=3.12
Requires-Dist: mcp[cli]>=1.2.0
Requires-Dist: httpx
Requires-Dist: python-dotenv
